shapes3d/__init__.py
shapes3d/shapes3_area.py
shapes3d-0.1.0.dist-info/METADATA
shapes3d-0.1.0.dist-info/WHEEL
shapes3d-0.1.0.dist-info/top_level.txt
shapes3d-0.1.0.dist-info/RECORD
